[
    {
        "id": 1,
        "type": "phone",
        "image": "galaxy6-black.jpg",
        "desc": "Samsung Galaxy S6 SM-G920i Unlocked Cellphone, 32GB, Black Sapphire",
        "price": 545.63,
        "color": "Black Sapphire",
        "availableColors": ["Black Sapphire", "Gold", "White", "Blue Topez"],
        "specs": [
            "Reimagined Design Inside and Out",
            "5.1\" Quad HD Super AMOLED display",
            "16MP rear-facing camera",
            "Unlocked cell phones are compatible with GSM carriers like AT&T and T-Mobile as well as with GSM SIM cards (e.g. H20, Straight Talk, and select prepaid carriers). Unlocked cell phones will not work with CDMA Carriers like Sprint, Verizon, Boost or Virgin."
            ],
        "stock": 10
    },
    {
        "id": 2,
        "type": "phone",
        "image": "galaxy6-gold.jpg",
        "desc": "Samsung Galaxy S6 G920I - 32GB - Factory Unlocked - GSM - Platinum Gold",
        "price": 545.00,
        "color": "Gold",
        "availableColors": ["Black Sapphire", "Gold", "White", "Blue Topez"],
        "specs": [
            "Reimagined Design Inside and Out",
            "5.1\" Quad HD Super AMOLED display",
            "16MP rear-facing camera"
            ],
        "stock": 4
    },
    {
        "id": 3,
        "type": "phone",
        "image": "edge-white.jpg",
        "desc": "Samsung Galaxy S6 Edge, White Pearl 32GB",
        "price": 699.99,
        "color": "White Pearl",
        "availableColors": ["Black", "Gold", "White Pearl"],
        "specs": [
            ],
        "stock": 16
    },
    {
        "id": 4,
        "type": "case",
        "image": "galaxy6-case-clear.jpg",
        "desc": "Samsung Galaxy S6 case, Nupro Lightweight Protective Snap-on Case for Galaxy S6 - Clear",
        "price": 9.99,
        "color": "Clear",
        "availableColors": ["Black", "Gold", "White", "Clear", "Red", "Blue"],
        "specs": [
            "Made with durable polycarbonate plastic",
            "Snap on design for a quick and easy installation",
            "Will not fit Samsung Galaxy S6 Edge"
            ],
        "stock": 1001
    },
    {
        "id": 5,
        "type": "phone",
        "image": "edge-gold.jpg",
        "desc": "Samsung Galaxy S6 Edge G925F Unlocked Cellphone, 32GB, Gold Platinum",
        "price": 669.79,
        "color": "Gold Platinum",
        "availableColors": ["Black", "Gold Platinum", "White Pearl", "Emerald Green"],
        "specs": [
            "2G: GSM 850 / 900 / 1800 / 1900, 3G: HSDPA 850 / 900 / 1900 / 2100, 4G: LTE Cat6 700 / 800 / 850 / 900 / 1700 (AWS) / 1800 / 1900 / 2100 / 2600 (Bands 1, 2, 3, 4, 5, 7, 8, 12, 17 18, 19, 20, 26)",
            "5.1-inch Super AMOLED Curved Edge, Multi-Touchscreen w/ Fingerprint sensor, Samsung Pay and Protective Corning Gorilla Glass 4",
            "Android v5.0.2 (Lollipop), Quad-Core 1.5 GHz Cortex-A53 + Quad-Core 2.1 GHz Cortex-A57 Processor, Chipset: Exynos 742, Mali-T760 Graphics",
            "16 Megapixel Camera (2988 x 5312 pixels) + Front-Facing 5 Megapixel Camera w/ Dual-Video, Auto HDR, Panorama, and Optical Image Stabilization",
            "Internal Memory: 32GB, 3GB RAM (not expandable)"
            ],
        "stock": 54
    },
    {
        "id": 5,
        "type": "case",
        "image": "galaxy6-case-green.jpg",
        "desc": "Samsung Galaxy S6 case, Nupro Lightweight Protective Snap-on Case for Galaxy S6 - Mint",
        "price": 8.99,
        "color": "Mint",
        "availableColors": ["Black", "Mint", "White", "Green", "Rose"],
        "specs": [
            "Made with durable polycarbonate plastic",
            "Snap on design for a quick and easy installation",
            "Will not fit Samsung Galaxy S6 Edge"
            ],
        "stock": 9
    },
    {
        "id": 6,
        "type": "case",
        "image": "galaxy6-case-black.jpg",
        "desc": "Samsung Galaxy S6 case, Nupro Lightweight Protective Snap-on Case for Galaxy S6 - Black",
        "price": 7.99,
        "color": "Black",
        "availableColors": ["Black", "Mint", "White", "Green", "Rose"],
        "specs": [
            "Made with durable polycarbonate plastic",
            "Snap on design for a quick and easy installation",
            "Will not fit Samsung Galaxy S6 Edge"
            ],
        "stock": 9
    },
    {
        "id": 7,
        "type": "phone",
        "image": "iphone-6-silver.jpg",
        "desc": "Apple iPhone 6, Silver, 16 GB (Unlocked)",
        "price": 699.99,
        "color": "Silver",
        "availableColors": ["Black", "Silver", "Gold", "White"],
        "specs": [
            "4.7-inch (diagonal) LED-backlit widescreen Multi-Touch display with IPS technology",
            "New 8-megapixel iSight camera with 1.5µ pixels",
            "A8 chip with 64-bit architecture. M8 motion coprocessor",
            "1080p HD video recording (30 fps or 60 fps)",
            "Unlocked cell phones are compatible with GSM carriers like AT&T and T-Mobile as well as with GSM SIM cards (e.g. H20 and select prepaid carriers). Unlocked cell phones will not work with CDMA Carriers like Sprint, Verizon, Boost or Virgin."
            ],
        "stock": 9
    },
    {
        "id": 8,
        "type": "phone",
        "image": "iphone-6-plus-black.jpg",
        "desc": "Apple iPhone 6 Plus 64GB 4G LTE Factory Unlocked GSM Smartphone - Space Gray",
        "price": 905.00,
        "color": "Space Gray",
        "availableColors": ["Black", "Silver", "Space Gray"],
        "specs": [
            "2G: GSM 850 / 900 / 1800 / 1900, 3G: HSDPA 850 / 900 / 1700 / 1900 / 2100, 4G: LTE 700 / 800 / 850 / 900 / 1700 / 1800 / 1900 / 2100 / 2600",
            "5.5\" LED-backlit IPS LCD Multi-Touchscreen Shatter proof glass, oleophobic coating",
            "iOS 8, Dual-Core 1.4 GHz Cyclone (ARM v8-based) Processor, Chipset: Apple A8, PowerVR GX6650 (hexa-core graphics) Graphics",
            "8 Megapixel Camera (3264 x 2448 pixels) w/ Autofocus, Dual-LED (Dual tone) Flash + Front-Facing 1.2 Megapixel Camera, 720p, burst, HDR",
            "Internal Memory: 64GB, 1GB RAM",
            "Unlocked cell phones are compatible with GSM carriers like AT&T and T-Mobile as well as with GSM SIM cards (e.g. H20, Straight Talk, and select prepaid carriers). Unlocked cell phones will not work with CDMA Carriers like Sprint, Verizon, Boost or Virgin."
            ],
        "stock": 5
    },
    {
        "id": 9,
        "type": "case",
        "image": "iphone-6-case-green.jpg",
        "desc": "iPhone 6 Case, Lumsing™ Hybrid High Impact Dual Layer Armor Defender Case Protective Cover for Apple iPhone 6 (4.7 inch Screen) with Screen Protector (Mint Green-Grey)",
        "price": 7.99,
        "color": "Black",
        "availableColors": ["Black", "Mint", "White", "Green", "Rose"],
        "specs": [
            "Specifically designed for the apple iphone 6 4.7 inch (will not fit any other phones)",
            "Double Protection: hard plastic case outside and soft rubber gel silicone skin inside",
            "Perfect fit and easy access to all ports, sensors, speakers, cameras",
            "Precise and Cute Design",
            "Super comfortable hand feeling and quality guarantee"
            ],
        "stock": 3
    },
    {
        "id": 10,
        "type": "case",
        "image": "iphone-6-plus-case-gold.jpg",
        "desc": "6 Plus Case, iPhone 6 Plus Case, SGM (TM) [Slim Hybrid] Case for iphone 6 Plus 5.5 [Clear Case] - iPhone 6 Plus Bumper Case - With SGM (TM) Microfiber Cleaning Cloth (Hot Pink)",
        "price": 12.99,
        "color": "Hot Pink",
        "availableColors": ["Hot Pink", "Cool Mint"],
        "specs": [
            "Clear case with combination of flexible TPU and hard Polycarbonate",
            "Provides ultimate protection from scratches, bumps, shocks and its mold keeps the phone trim and trendy",
            "Precisely cut to preserve full use of volume buttons, charger, camera, microphone, headphone jack, and all other ports",
            "Super slim design that adds minimal bulky to the phone while easily slides in and out of pockets",
            "Designed to fit Apple iPhone 6 - 5.5\" (2014)"
            ],
        "stock": 1003
    }
]